mongomoron/__init__.py
mongomoron/connection.py
mongomoron/expression.py
mongomoron-0.4.dist-info/LICENSE.txt
mongomoron-0.4.dist-info/METADATA
mongomoron-0.4.dist-info/WHEEL
mongomoron-0.4.dist-info/top_level.txt
mongomoron-0.4.dist-info/RECORD
