Metadata-Version: 2.1
Name: mongomoron
Version: 0.4
Summary: Vanilla wrapper around pymongo
Home-page: https://github.com/ilyaukin/mongomoron
Author: Ilya Lyaukin
Author-email: kzerby@gmail.com
License: UNKNOWN
Platform: UNKNOWN
Requires-Python: >=3.6
License-File: LICENSE.txt
